sanic_function_deps/__init__.py
sanic_function_deps/function_helper.py
sanic_function_deps-0.2.2.dist-info/WHEEL
sanic_function_deps-0.2.2.dist-info/METADATA
sanic_function_deps-0.2.2.dist-info/RECORD
