Metadata-Version: 2.1
Name: sanic-function-deps
Version: 0.2.2
Summary: Directly inject your query params & headers into your router function
License: MIT
Author: Erik Lilja
Author-email: erikvlilja@gmail.com
Requires-Python: >=3.6,<4.0
Classifier: License :: OSI Approved :: MIT License
Classifier: Programming Language :: Python :: 3
Classifier: Programming Language :: Python :: 3.6
Classifier: Programming Language :: Python :: 3.7
Classifier: Programming Language :: Python :: 3.8
Requires-Dist: sanic (>=19.12.2,<20.0.0)
